buildster/__init__.py
buildster/__main__.py
buildster/buildster.py
buildster/command_line.py
buildster/internal/__init__.py
buildster/internal/architecture.py
buildster/internal/argument.py
buildster/internal/argument_list.py
buildster/internal/base.py
buildster/internal/branch.py
buildster/internal/build.py
buildster/internal/build_instruction.py
buildster/internal/cmake_build_instruction.py
buildster/internal/command_build_instruction.py
buildster/internal/commands_build_instruction.py
buildster/internal/component.py
buildster/internal/component_list.py
buildster/internal/content.py
buildster/internal/context.py
buildster/internal/copier.py
buildster/internal/copier_destination.py
buildster/internal/copier_rename.py
buildster/internal/copier_source.py
buildster/internal/credentials.py
buildster/internal/definition.py
buildster/internal/definition_list.py
buildster/internal/deleter.py
buildster/internal/dependency.py
buildster/internal/dependency_list.py
buildster/internal/destination.py
buildster/internal/downloader.py
buildster/internal/element.py
buildster/internal/exception.py
buildster/internal/exception_list.py
buildster/internal/executable_target.py
buildster/internal/export_list.py
buildster/internal/extractor.py
buildster/internal/generator.py
buildster/internal/git_repo_dependency.py
buildster/internal/hint.py
buildster/internal/hint_list.py
buildster/internal/import_list.py
buildster/internal/key.py
buildster/internal/label.py
buildster/internal/library_target.py
buildster/internal/link.py
buildster/internal/link_list.py
buildster/internal/list.py
buildster/internal/local_dependency.py
buildster/internal/module.py
buildster/internal/module_list.py
buildster/internal/native.py
buildster/internal/native_list.py
buildster/internal/object.py
buildster/internal/package.py
buildster/internal/package_list.py
buildster/internal/password.py
buildster/internal/path.py
buildster/internal/performer.py
buildster/internal/project.py
buildster-1.5.dist-info/LICENSE
buildster-1.5.dist-info/METADATA
buildster-1.5.dist-info/WHEEL
buildster-1.5.dist-info/entry_points.txt
buildster-1.5.dist-info/top_level.txt
buildster-1.5.dist-info/zip-safe
buildster-1.5.dist-info/RECORD
