Metadata-Version: 2.1
Name: buildster
Version: 1.5
Summary: Buildster: Software Project Construction Automation
Home-page: https://github.com/PierceLBrooks/Buildster
Author: Pierce L. Brooks
Author-email: piercebrks@gmail.com
Maintainer: Pierce L. Brooks
Maintainer-email: piercebrks@gmail.com
License: MIT
Classifier: Environment :: Console
Classifier: License :: OSI Approved :: MIT License
Classifier: Intended Audience :: Developers
Classifier: Topic :: Software Development
License-File: LICENSE
Requires-Dist: patool
Requires-Dist: pyunpack
